{"cameraMode":{"drawMode":0,"name":"Shaded","section":"Shading Mode"},"sceneLighting":true,"audioPlay":false,"sceneViewState":{"showFog":true,"showMaterialUpdate":false,"showSkybox":true,"showFlares":true,"showImageEffects":true,"showParticleSystems":true},"in2DMode":false,"pivot":{"x":76.02088165283203,"y":15.77902603149414,"z":76.35478973388672},"rotation":{"x":-0.2616605758666992,"y":0.03271842002868652,"z":-0.008875829167664051,"w":-0.964565098285675},"size":91.68151092529297,"orthographic":false}